Test_FiinQuant/FiinDataHistorical.py
Test_FiinQuant/FiinDataHistorical.pyi
Test_FiinQuant/FiinIndicator.py
Test_FiinQuant/FiinIndicator.pyi
Test_FiinQuant/FiinSession.py
Test_FiinQuant/FiinSession.pyi
Test_FiinQuant/HistoricalReturnData.py
Test_FiinQuant/HistoricalReturnData.pyi
Test_FiinQuant/RealTimeReturnData.py
Test_FiinQuant/RealTimeReturnData.pyi
Test_FiinQuant/SubscribeForRealTime.py
Test_FiinQuant/SubscribeForRealTime.pyi
Test_FiinQuant/__init__.py
Test_FiinQuant/pyarmor_runtime_000000/__init__.py
Test_FiinQuant/pyarmor_runtime_000000/pyarmor_runtime.pyd
Test_FiinQuant-0.0.3.dist-info/METADATA
Test_FiinQuant-0.0.3.dist-info/WHEEL
Test_FiinQuant-0.0.3.dist-info/top_level.txt
Test_FiinQuant-0.0.3.dist-info/RECORD
